setup.py
apigateway/__init__.py
apigateway/admin.py
apigateway/models.py
apigateway/tests.py
apigateway/urls.py
apigateway/views.py
djangoapigateway.egg-info/PKG-INFO
djangoapigateway.egg-info/SOURCES.txt
djangoapigateway.egg-info/dependency_links.txt
djangoapigateway.egg-info/top_level.txt